odoo9_addon_account_bank_statement_import_fr_cfonb-9.0.0.1.1.99.dev11-py2.7-nspkg.pth
odoo9_addon_account_bank_statement_import_fr_cfonb-9.0.0.1.1.99.dev11.dist-info/METADATA
odoo9_addon_account_bank_statement_import_fr_cfonb-9.0.0.1.1.99.dev11.dist-info/RECORD
odoo9_addon_account_bank_statement_import_fr_cfonb-9.0.0.1.1.99.dev11.dist-info/WHEEL
odoo9_addon_account_bank_statement_import_fr_cfonb-9.0.0.1.1.99.dev11.dist-info/namespace_packages.txt
odoo9_addon_account_bank_statement_import_fr_cfonb-9.0.0.1.1.99.dev11.dist-info/top_level.txt
odoo_addons/account_bank_statement_import_fr_cfonb/README.rst
odoo_addons/account_bank_statement_import_fr_cfonb/__init__.py
odoo_addons/account_bank_statement_import_fr_cfonb/__openerp__.py
odoo_addons/account_bank_statement_import_fr_cfonb/account_bank_statement_import_fr_cfonb.py
odoo_addons/account_bank_statement_import_fr_cfonb/i18n/ca_ES.po
odoo_addons/account_bank_statement_import_fr_cfonb/i18n/fi.po
odoo_addons/account_bank_statement_import_fr_cfonb/i18n/fr.po
odoo_addons/account_bank_statement_import_fr_cfonb/i18n/nb_NO.po
odoo_addons/account_bank_statement_import_fr_cfonb/i18n/nl_NL.po
odoo_addons/account_bank_statement_import_fr_cfonb/static/description/icon.png
